API-Drone/__init__.py
API-Drone/vehicle.py
API_Drone/__init__.py
API_Drone/vehicle.py
API_Drone-0.0.3.dist-info/METADATA
API_Drone-0.0.3.dist-info/WHEEL
API_Drone-0.0.3.dist-info/top_level.txt
API_Drone-0.0.3.dist-info/RECORD
